simplejpeg/_jpeg.pyi
simplejpeg/__init__.py
simplejpeg/_jpeg.cpython-310-darwin.so
simplejpeg-1.9.0.dist-info/RECORD
simplejpeg-1.9.0.dist-info/WHEEL
simplejpeg-1.9.0.dist-info/top_level.txt
simplejpeg-1.9.0.dist-info/METADATA
simplejpeg-1.9.0.dist-info/licenses/LICENSE
