Metadata-Version: 2.4
Name: simplejpeg
Version: 1.9.0
Summary: A simple package for fast JPEG encoding and decoding.
Author-email: Joachim Folz <joachim.folz@dfki.de>
License-Expression: MIT
Project-URL: Documentation, https://github.com/jfolz/simplejpeg/blob/master/README.rst
Project-URL: Source, https://github.com/jfolz/simplejpeg
Project-URL: Tracker, https://github.com/jfolz/simplejpeg/issues
Keywords: the,fastest,JPEG,encoding,decoding,package,in,town
Classifier: Development Status :: 5 - Production/Stable
Classifier: Intended Audience :: Science/Research
Requires-Python: >=3.9
License-File: LICENSE
Requires-Dist: numpy>=1.19.3
Dynamic: license-file
Dynamic: requires-dist
